myfunctionfolder/__init__.py
myfunctionfolder/myfunction.py
myfunctionfolder/myfunction_click.py
addCodeReact-1.0.3.dist-info/LICENSE
addCodeReact-1.0.3.dist-info/METADATA
addCodeReact-1.0.3.dist-info/WHEEL
addCodeReact-1.0.3.dist-info/entry_points.txt
addCodeReact-1.0.3.dist-info/top_level.txt
addCodeReact-1.0.3.dist-info/RECORD
